_losses/__init__.py
_losses/_spectralnet_loss.py
_models/__init__.py
_models/_ae_model.py
_models/_spectralnet_model.py
_trainers/__init__.py
_trainers/_ae_trainer.py
_trainers/_spectralnet_trainer.py
_trainers/_trainer.py
scase/__init__.py
scase/_cluster.py
scase/_metrics.py
scase/_reduction.py
scase/_utils.py
scase/_losses/__init__.py
scase/_losses/_spectralnet_loss.py
scase/_models/__init__.py
scase/_models/_ae_model.py
scase/_models/_spectralnet_model.py
scase/_trainers/__init__.py
scase/_trainers/_ae_trainer.py
scase/_trainers/_spectralnet_trainer.py
scase/_trainers/_trainer.py
spectralnet/__init__.py
spectralnet/_cluster.py
spectralnet/_metrics.py
spectralnet/_reduction.py
spectralnet/_utils.py
spectralnet/_losses/__init__.py
spectralnet/_losses/_spectralnet_loss.py
spectralnet/_models/__init__.py
spectralnet/_models/_ae_model.py
spectralnet/_models/_spectralnet_model.py
spectralnet/_trainers/__init__.py
spectralnet/_trainers/_ae_trainer.py
spectralnet/_trainers/_spectralnet_trainer.py
spectralnet/_trainers/_trainer.py
tests/__init__.py
scase-0.3.6.dist-info/LICENSE.md
scase-0.3.6.dist-info/METADATA
scase-0.3.6.dist-info/WHEEL
scase-0.3.6.dist-info/top_level.txt
scase-0.3.6.dist-info/RECORD
