Metadata-Version: 2.1
Name: scase
Version: 0.3.6
Summary: Spectral Embedding Using Deep Neural Networks
Home-page: https://github.com/shaham-lab/ScaSE.git
Author: Nir Ben-Ari
Project-URL: Bug Tracker, https://github.com/shaham-lab/ScaSE/issues
Classifier: Programming Language :: Python :: 3
Classifier: License :: OSI Approved :: MIT License
Classifier: Operating System :: OS Independent
Requires-Python: >=3.11
License-File: LICENSE.md
